[
  {
    "contentType": "MULTIPLE_CHOICE",
    "level": "N",
    "sourceUrl": "https://www.ytn.co.kr/_ln/0102_202512261849402655",
    "contents": [
      {
        "contentId": 1,
        "question": "쿠팡이 성탄절에 발표한 조사의 성격은 무엇인가?",
        "options": [
          {
            "label": "A",
            "text": "공동 연구 조사"
          },
          {
            "label": "B",
            "text": "국제 협력 조사"
          },
          {
            "label": "C",
            "text": "자체 조사"
          },
          {
            "label": "D",
            "text": "정부 주도 조사"
          }
        ],
        "correctAnswer": "C",
        "answerExplanation": "쿠팡의 성탄절 발표는 정부 조사와 무관한 자체 조사였다.",
        "sourceUrl": "https://www.ytn.co.kr/_ln/0102_202512261849402655"
      },
      {
        "contentId": 2,
        "question": "쿠팡이 유출자의 노트북을 회수한 이유는 무엇인가?",
        "options": [
          {
            "label": "A",
            "text": "기술 개발 목적"
          },
          {
            "label": "B",
            "text": "고객 서비스 개선"
          },
          {
            "label": "C",
            "text": "정보 유출 확인"
          },
          {
            "label": "D",
            "text": "보안 시스템 업그레이드"
          }
        ],
        "correctAnswer": "C",
        "answerExplanation": "쿠팡은 유출자의 노트북을 회수하여 정보 유출을 확인했다.",
        "sourceUrl": "https://www.ytn.co.kr/_ln/0102_202512261849402655"
      },
      {
        "contentId": 3,
        "question": "쿠팡이 정부와 협력한 시점은 언제인가?",
        "options": [
          {
            "label": "A",
            "text": "조사 일지 공개 후"
          },
          {
            "label": "B",
            "text": "노트북 회수 전"
          },
          {
            "label": "C",
            "text": "성탄절 이후"
          },
          {
            "label": "D",
            "text": "공문 수령 후"
          }
        ],
        "correctAnswer": "D",
        "answerExplanation": "쿠팡은 공문을 받은 후 정부와 협력했다.",
        "sourceUrl": "https://www.ytn.co.kr/_ln/0102_202512261849402655"
      },
      {
        "contentId": 4,
        "question": "쿠팡의 성탄절 발표에 대한 비판의 주된 내용은 무엇인가?",
        "options": [
          {
            "label": "A",
            "text": "정보 유출 은폐"
          },
          {
            "label": "B",
            "text": "정부의 지시 위반"
          },
          {
            "label": "C",
            "text": "셀프 면죄부"
          },
          {
            "label": "D",
            "text": "고객 서비스 부족"
          }
        ],
        "correctAnswer": "C",
        "answerExplanation": "쿠팡의 발표는 '셀프 면죄부'라는 비판을 받았다.",
        "sourceUrl": "https://www.ytn.co.kr/_ln/0102_202512261849402655"
      },
      {
        "contentId": 5,
        "question": "쿠팡이 공개한 조사 일지의 주요 내용은 무엇인가?",
        "options": [
          {
            "label": "A",
            "text": "고객 불만 사항"
          },
          {
            "label": "B",
            "text": "유출 정보의 수량"
          },
          {
            "label": "C",
            "text": "정부의 조사 결과"
          },
          {
            "label": "D",
            "text": "기술 개발 계획"
          }
        ],
        "correctAnswer": "B",
        "answerExplanation": "조사 일지에는 유출 정보의 수량이 포함되어 있다.",
        "sourceUrl": "https://www.ytn.co.kr/_ln/0102_202512261849402655"
      }
    ]
  }
]