{
  "contentType": "SENTENCE_COMPLETION",
  "level": "E",
  "contents": [
    [
      {
        "contentId": "1",
        "question": "원·달러 환율이 24일 급락한 이유는 ______",
        "referenceAnswer": "연말 한산한 시장 속 당국 조치 영향이다."
      },
      {
        "contentId": "2",
        "question": "정규장 마감 시 원·달러 환율은 ______",
        "referenceAnswer": "1440.35원으로 마감했다."
      },
      {
        "contentId": "3",
        "question": "외국인이 국내주식시장에서 '사자'를 보인 이유는 ______",
        "referenceAnswer": "삼성전자가 최고가를 경신했기 때문이다."
      }
    ]
  ]
}