[
  {
    "contentType": "SHORT_ANSWER",
    "level": "E",
    "sourceUrl": "http://www.inews24.com/view/1910467",
    "contents": [
      {
        "contentId": "1",
        "question": "광산구의회가 추진하는 프로그램의 주요 목표로 지역 사회의 어떤 능력을 강화하려는 것입니까?",
        "correctAnswer": "지역 문제",
        "answerExplanation": "지역 문제 해결 능력은 지역 사회의 지속 가능한 발전을 도모한다.",
        "sourceUrl": "http://www.inews24.com/view/1910467"
      },
      {
        "contentId": "2",
        "question": "정치 리터러시 교육에서 두드러진 성과로 평가된 요소는 무엇입니까?",
        "correctAnswer": "정책 혁신성",
        "answerExplanation": "정책 혁신성은 교육 프로그램의 창의적 접근을 강조한다.",
        "sourceUrl": "http://www.inews24.com/view/1910467"
      },
      {
        "contentId": "3",
        "question": "의회가 주도하여 청소년의 정치적 이해를 높이는 교육 모델로 장려상을 수상한 유형은 무엇입니까?",
        "correctAnswer": "의회주도형",
        "answerExplanation": "의회주도형 모델은 청소년의 정치적 이해를 증진시키는 데 기여한다.",
        "sourceUrl": "http://www.inews24.com/view/1910467"
      },
      {
        "contentId": "4",
        "question": "정치적 참여와 비판적 사고 함양을 목표로 본심사에 진출한 프로그램은 무엇입니까?",
        "correctAnswer": "청소년 정치아카데미",
        "answerExplanation": "청소년 정치아카데미는 정치 교육을 통해 참여 의식을 고취한다.",
        "sourceUrl": "http://www.inews24.com/view/1910467"
      },
      {
        "contentId": "5",
        "question": "정치 리터러시 교육의 확장을 위해 광산구의회가 협력할 계획인 기관은 무엇입니까?",
        "correctAnswer": "청소년 기관",
        "answerExplanation": "청소년 기관과의 협력은 교육의 접근성과 효과성을 증대한다.",
        "sourceUrl": "http://www.inews24.com/view/1910467"
      }
    ]
  }
]